ex3/fulladder.v
module fulladder( sum, co, a, b, ci);

  input   a, b, ci;
  output  sum, co;

  reg co, sum;

  always @(a or b or ci) begin
    {co, sum} = a + b + ci;
  end

endmodule

ex3/fulladder_tb.v
module main;
  reg A, B, CI;
  wire SUM, CO;
  
  fulladder fa(SUM, CO, A, B, CI);

  initial begin
    $monitor("time=%d:sum = %b + %b + %b = %b, co = %b\n", $time, A, B, CI, SUM, CO);
    $dumpfile("waves.vcd");
    $dumpvars;
    A = 0; B = 0; CI = 0;
    #5
    A = 0; B = 0; CI = 1;
    #5
    A = 0; B = 1; CI = 0;
    #5
    A = 0; B = 1; CI = 1;
    #5
    A = 1; B = 0; CI = 0;
    #5
    A = 1; B = 0; CI = 1;
    #5
    A = 1; B = 1; CI = 0;
    #5
    A = 1; B = 1; CI = 1;
    #5
    $finish;
  end
endmodule

ex3/waves.vcd
$date
	Fri Dec 23 15:09:25 2022
$end
$version
	Icarus Verilog
$end
$timescale
	1s
$end
$scope module main $end
$var wire 1 ! SUM $end
$var wire 1 " CO $end
$var reg 1 # A $end
$var reg 1 $ B $end
$var reg 1 % CI $end
$scope module fa $end
$var wire 1 # a $end
$var wire 1 $ b $end
$var wire 1 % ci $end
$var reg 1 " co $end
$var reg 1 ! sum $end
$upscope $end
$upscope $end
$enddefinitions $end
#0
$dumpvars
0%
0$
0#
0"
0!
$end
#5
1!
1%
#10
0%
1$
#15
1"
0!
1%
#20
0"
1!
0%
0$
1#
#25
1"
0!
1%
#30
0%
1$
#35
1!
1%
