ex3/fulladder.v
module fulladder( sum, co, a, b, ci);

  input   a, b, ci;
  output  sum, co;

  reg co, sum;

  always @(a or b or ci) begin
    {co, sum} = a + b + ci;
  end

endmodule

ex4/add4.v
`include "../ex3/fulladder.v"

module  add4( sum, co, a, b, ci);

  input   [3:0] a, b;
  input   ci;
  output  [3:0] sum;
  output  co;

  wire [2:0] c;

  fulladder fa0(sum[0], c[0], a[0], b[0], ci);
  fulladder fa1(sum[1], c[1], a[1], b[1], c[0]);
  fulladder fa2(sum[2], c[2], a[2], b[2], c[1]);
  fulladder fa3(sum[3], co, a[3], b[3], c[2]);

endmodule

ex5/addsub.v
`include "../ex4/add4.v"

module	addsub( result, operand_a, operand_b, mode );

	input	[3:0]	operand_a, operand_b;
	input	mode;
	output	[3:0]	result;
	wire co;
	wire	[3:0]	xor_b;

	xor	g0(xor_b[0], operand_b[0], mode);
	xor	g1(xor_b[1], operand_b[1], mode);
	xor	g2(xor_b[2], operand_b[2], mode);
	xor	g3(xor_b[3], operand_b[3], mode);
	
	add4	m1(
		.sum(result),
		.co(co),
		.a(operand_a),	 
		.b(xor_b),	
		.ci(mode)
	);	
endmodule

ex5/addsub_tb.v
module	addsub_tb;
	
	// for DUT port connection
	reg					mode;
	reg 	[3:0]	operand_a, operand_b;
	wire	[3:0] result;
	wire co;
	
	// for pattern generation
	integer			a, b, expect, error_num, t;
	reg					overflow;
	wire	[3:0]	expect_out = expect[3:0];	// compare "expect_out" with "result"

	addsub as(result, operand_a, operand_b, mode);

	// give stimulus pattern
	initial begin
	error_num = 0;

	$dumpfile("waves.vcd");
	$dumpvars;

	$display( "\nTest subtraction mode." );
	#10 mode = 1'b1;
	
	for( a=-8; a<=7; a=a+1 ) begin
		for( b=-8; b<=7; b=b+1 ) begin
			
			operand_a = a[3:0];
			operand_b = b[3:0];
			expect = a - b;
	
			#1;
			if( expect >= -8 && expect <= 7 ) begin
				overflow = 1'b0;
				if( expect[3:0] !== result ) begin
					error_num = error_num + 1;
					$display( "Error(%d):(%d)-(%d) Expect(%b) Output(%b)", error_num[9:0], a, b, expect[3:0], result );
				end
			end	else begin
				overflow = 1'b1;
			end
	
			#1;
		end
	end

	$display( "\nTest addition mode." );
	mode = 1'b0;
	
	for( a=-8; a<=7; a=a+1 ) begin
		for( b=-8; b<=7; b=b+1 ) begin
			
			operand_a = a[3:0];
			operand_b = b[3:0];
			expect = a + b;
	
			#1;
			if( expect >= -8 && expect <= 7 ) begin
				overflow = 1'b0;
				if( expect[3:0] !== result ) begin
					error_num = error_num + 1;
					$display( "Error(%d):(%d)+(%d) Expect(%b) Output(%b)", error_num[9:0], a, b, expect[3:0], result );
				end
			end	else begin
				overflow = 1'b1;
			end
	
			#1;
		end
	end
	
	if( error_num==0 )
		$display( "\nPass all test\n" );
	else
		$display( "\nFail, error number = %d\n", error_num );
	
	#10 $finish;
	end

endmodule

ex5/waves.vcd
$date
	Fri Dec 23 15:31:14 2022
$end
$version
	Icarus Verilog
$end
$timescale
	1s
$end
$scope module addsub_tb $end
$var wire 4 ! result [3:0] $end
$var wire 4 " expect_out [3:0] $end
$var reg 1 # mode $end
$var reg 4 $ operand_a [3:0] $end
$var reg 4 % operand_b [3:0] $end
$var reg 1 & overflow $end
$var integer 32 ' a [31:0] $end
$var integer 32 ( b [31:0] $end
$var integer 32 ) error_num [31:0] $end
$var integer 32 * expect [31:0] $end
$scope module as $end
$var wire 1 # mode $end
$var wire 4 + operand_a [3:0] $end
$var wire 4 , operand_b [3:0] $end
$var wire 4 - xor_b [3:0] $end
$var wire 4 . result [3:0] $end
$var wire 1 / co $end
$scope module m1 $end
$var wire 4 0 a [3:0] $end
$var wire 4 1 b [3:0] $end
$var wire 1 # ci $end
$var wire 4 2 sum [3:0] $end
$var wire 1 / co $end
$var wire 3 3 c [2:0] $end
$scope module fa0 $end
$var wire 1 4 a $end
$var wire 1 5 b $end
$var wire 1 # ci $end
$var reg 1 6 co $end
$var reg 1 7 sum $end
$upscope $end
$scope module fa1 $end
$var wire 1 8 a $end
$var wire 1 9 b $end
$var wire 1 : ci $end
$var reg 1 ; co $end
$var reg 1 < sum $end
$upscope $end
$scope module fa2 $end
$var wire 1 = a $end
$var wire 1 > b $end
$var wire 1 ? ci $end
$var reg 1 @ co $end
$var reg 1 A sum $end
$upscope $end
$scope module fa3 $end
$var wire 1 B a $end
$var wire 1 C b $end
$var wire 1 D ci $end
$var reg 1 / co $end
$var reg 1 E sum $end
$upscope $end
$upscope $end
$upscope $end
$upscope $end
$enddefinitions $end
#0
$dumpvars
xE
xD
xC
xB
xA
x@
x?
x>
x=
x<
x;
x:
x9
x8
x7
x6
x5
x4
bx 3
bx 2
bx 1
bx 0
x/
bx .
bx -
bx ,
bx +
bx *
b0 )
bx (
bx '
x&
bx %
bx $
x#
bx "
bx !
$end
#10
1/
0E
1D
1@
0A
1?
1;
0<
1:
b111 3
16
b0 !
b0 .
b0 2
07
15
19
1>
0C
b111 -
b111 1
b0 "
04
08
0=
1B
b0 *
b1000 %
b1000 ,
b1000 $
b1000 +
b1000 0
b11111111111111111111111111111000 (
b11111111111111111111111111111000 '
1#
#11
0&
#12
0/
1E
0D
0@
1A
0?
0;
1<
0:
b0 3
06
b1111 !
b1111 .
b1111 2
17
05
b110 -
b110 1
b1111 "
b11111111111111111111111111111111 *
b1001 %
b1001 ,
b11111111111111111111111111111001 (
#14
1:
b1 3
16
07
b1110 !
b1110 .
b1110 2
1<
15
09
b101 -
b101 1
b1110 "
b11111111111111111111111111111110 *
b1010 %
b1010 ,
b11111111111111111111111111111010 (
#16
0<
0:
b0 3
06
b1101 !
b1101 .
b1101 2
17
05
b100 -
b100 1
b1101 "
b11111111111111111111111111111101 *
b1011 %
b1011 ,
b11111111111111111111111111111011 (
#18
1?
1;
1:
b11 3
16
07
0<
b1100 !
b1100 .
b1100 2
1A
15
19
0>
b11 -
b11 1
b1100 "
b11111111111111111111111111111100 *
b1100 %
b1100 ,
b11111111111111111111111111111100 (
#20
0A
0?
0;
1<
0:
b0 3
06
b1011 !
b1011 .
b1011 2
17
05
b10 -
b10 1
b1011 "
b11111111111111111111111111111011 *
b1101 %
b1101 ,
b11111111111111111111111111111101 (
#22
1:
b1 3
16
07
b1010 !
b1010 .
b1010 2
1<
15
09
b1 -
b1 1
b1010 "
b11111111111111111111111111111010 *
b1110 %
b1110 ,
b11111111111111111111111111111110 (
#24
0<
0:
b0 3
06
b1001 !
b1001 .
b1001 2
17
05
b0 -
b0 1
b1001 "
b11111111111111111111111111111001 *
b1111 %
b1111 ,
b11111111111111111111111111111111 (
#26
1D
1@
1?
1;
1:
b111 3
16
07
0<
0A
1/
b1000 !
b1000 .
b1000 2
1E
15
19
1>
1C
b1111 -
b1111 1
b1000 "
b11111111111111111111111111111000 *
b0 %
b0 ,
b0 (
#28
0E
0D
0@
1A
0?
0;
1<
0:
b0 3
06
b111 !
b111 .
b111 2
17
05
b1110 -
b1110 1
b111 "
b11111111111111111111111111110111 *
b1 %
b1 ,
b1 (
#29
1&
#30
1:
b1 3
16
07
b110 !
b110 .
b110 2
1<
15
09
b1101 -
b1101 1
b110 "
b11111111111111111111111111110110 *
b10 %
b10 ,
b10 (
#32
0<
0:
b0 3
06
b101 !
b101 .
b101 2
17
05
b1100 -
b1100 1
b101 "
b11111111111111111111111111110101 *
b11 %
b11 ,
b11 (
#34
1?
1;
1:
b11 3
16
07
0<
b100 !
b100 .
b100 2
1A
15
19
0>
b1011 -
b1011 1
b100 "
b11111111111111111111111111110100 *
b100 %
b100 ,
b100 (
#36
0A
0?
0;
1<
0:
b0 3
06
b11 !
b11 .
b11 2
17
05
b1010 -
b1010 1
b11 "
b11111111111111111111111111110011 *
b101 %
b101 ,
b101 (
#38
1:
b1 3
16
07
b10 !
b10 .
b10 2
1<
15
09
b1001 -
b1001 1
b10 "
b11111111111111111111111111110010 *
b110 %
b110 ,
b110 (
#40
0<
0:
b0 3
06
b1 !
b1 .
b1 2
17
05
b1000 -
b1000 1
b1 "
b11111111111111111111111111110001 *
b111 %
b111 ,
b111 (
#42
1D
1@
1?
0A
1/
0E
1;
15
19
1>
0C
1:
b111 -
b111 1
b111 3
16
b1 !
b1 .
b1 2
17
14
b1 *
b1000 %
b1000 ,
b1001 $
b1001 +
b1001 0
b11111111111111111111111111111001 '
b11111111111111111111111111111000 (
#43
0&
#44
b0 !
b0 .
b0 2
07
05
b110 -
b110 1
b0 "
b0 *
b1001 %
b1001 ,
b11111111111111111111111111111001 (
#46
0/
1E
0D
0@
1A
0?
17
b1 3
0;
b1111 !
b1111 .
b1111 2
1<
15
09
b101 -
b101 1
b1111 "
b11111111111111111111111111111111 *
b1010 %
b1010 ,
b11111111111111111111111111111010 (
#48
b1110 !
b1110 .
b1110 2
07
05
b100 -
b100 1
b1110 "
b11111111111111111111111111111110 *
b1011 %
b1011 ,
b11111111111111111111111111111011 (
#50
1?
17
b11 3
1;
0<
b1101 !
b1101 .
b1101 2
1A
15
19
0>
b11 -
b11 1
b1101 "
b11111111111111111111111111111101 *
b1100 %
b1100 ,
b11111111111111111111111111111100 (
#52
b1100 !
b1100 .
b1100 2
07
05
b10 -
b10 1
b1100 "
b11111111111111111111111111111100 *
b1101 %
b1101 ,
b11111111111111111111111111111101 (
#54
0A
0?
17
b1 3
0;
b1011 !
b1011 .
b1011 2
1<
15
09
b1 -
b1 1
b1011 "
b11111111111111111111111111111011 *
b1110 %
b1110 ,
b11111111111111111111111111111110 (
#56
b1010 !
b1010 .
b1010 2
07
05
b0 -
b0 1
b1010 "
b11111111111111111111111111111010 *
b1111 %
b1111 ,
b11111111111111111111111111111111 (
#58
1D
1@
1?
17
b111 3
1;
0<
0A
1/
b1001 !
b1001 .
b1001 2
1E
15
19
1>
1C
b1111 -
b1111 1
b1001 "
b11111111111111111111111111111001 *
b0 %
b0 ,
b0 (
#60
b1000 !
b1000 .
b1000 2
07
05
b1110 -
b1110 1
b1000 "
b11111111111111111111111111111000 *
b1 %
b1 ,
b1 (
#62
0E
0D
0@
1A
0?
17
b1 3
0;
b111 !
b111 .
b111 2
1<
15
09
b1101 -
b1101 1
b111 "
b11111111111111111111111111110111 *
b10 %
b10 ,
b10 (
#63
1&
#64
b110 !
b110 .
b110 2
07
05
b1100 -
b1100 1
b110 "
b11111111111111111111111111110110 *
b11 %
b11 ,
b11 (
#66
1?
17
b11 3
1;
0<
b101 !
b101 .
b101 2
1A
15
19
0>
b1011 -
b1011 1
b101 "
b11111111111111111111111111110101 *
b100 %
b100 ,
b100 (
#68
b100 !
b100 .
b100 2
07
05
b1010 -
b1010 1
b100 "
b11111111111111111111111111110100 *
b101 %
b101 ,
b101 (
#70
0A
0?
17
b1 3
0;
b11 !
b11 .
b11 2
1<
15
09
b1001 -
b1001 1
b11 "
b11111111111111111111111111110011 *
b110 %
b110 ,
b110 (
#72
b10 !
b10 .
b10 2
07
05
b1000 -
b1000 1
b10 "
b11111111111111111111111111110010 *
b111 %
b111 ,
b111 (
#74
1D
1/
0E
1@
15
19
1>
0C
1:
1?
b111 -
b111 1
16
07
b111 3
1;
b10 !
b10 .
b10 2
1<
04
18
b10 *
b1000 %
b1000 ,
b1010 $
b1010 +
b1010 0
b11111111111111111111111111111010 '
b11111111111111111111111111111000 (
#75
0&
#76
0<
0:
b110 3
06
b1 !
b1 .
b1 2
17
05
b110 -
b110 1
b1 "
b1 *
b1001 %
b1001 ,
b11111111111111111111111111111001 (
#78
1/
0E
1D
1@
0A
1:
1?
16
07
b111 3
1;
b0 !
b0 .
b0 2
0<
15
09
b101 -
b101 1
b0 "
b0 *
b1010 %
b1010 ,
b11111111111111111111111111111010 (
#80
0/
1E
0D
0@
1A
0?
0;
1<
0:
b0 3
06
b1111 !
b1111 .
b1111 2
17
05
b100 -
b100 1
b1111 "
b11111111111111111111111111111111 *
b1011 %
b1011 ,
b11111111111111111111111111111011 (
#82
1:
1?
16
07
b11 3
1;
1<
b1110 !
b1110 .
b1110 2
1A
15
19
0>
b11 -
b11 1
b1110 "
b11111111111111111111111111111110 *
b1100 %
b1100 ,
b11111111111111111111111111111100 (
#84
0<
0:
b10 3
06
b1101 !
b1101 .
b1101 2
17
05
b10 -
b10 1
b1101 "
b11111111111111111111111111111101 *
b1101 %
b1101 ,
b11111111111111111111111111111101 (
#86
1A
1:
1?
16
07
b11 3
1;
b1100 !
b1100 .
b1100 2
0<
15
09
b1 -
b1 1
b1100 "
b11111111111111111111111111111100 *
b1110 %
b1110 ,
b11111111111111111111111111111110 (
#88
0A
0?
0;
1<
0:
b0 3
06
b1011 !
b1011 .
b1011 2
17
05
b0 -
b0 1
b1011 "
b11111111111111111111111111111011 *
b1111 %
b1111 ,
b11111111111111111111111111111111 (
#90
1D
1@
1:
1?
16
07
b111 3
1;
1<
0A
1/
b1010 !
b1010 .
b1010 2
1E
15
19
1>
1C
b1111 -
b1111 1
b1010 "
b11111111111111111111111111111010 *
b0 %
b0 ,
b0 (
#92
0<
0:
b110 3
06
b1001 !
b1001 .
b1001 2
17
05
b1110 -
b1110 1
b1001 "
b11111111111111111111111111111001 *
b1 %
b1 ,
b1 (
#94
1E
1D
1@
0A
1:
1?
16
07
b111 3
1;
b1000 !
b1000 .
b1000 2
0<
15
09
b1101 -
b1101 1
b1000 "
b11111111111111111111111111111000 *
b10 %
b10 ,
b10 (
#96
0E
0D
0@
1A
0?
0;
1<
0:
b0 3
06
b111 !
b111 .
b111 2
17
05
b1100 -
b1100 1
b111 "
b11111111111111111111111111110111 *
b11 %
b11 ,
b11 (
#97
1&
#98
1:
1?
16
07
b11 3
1;
1<
b110 !
b110 .
b110 2
1A
15
19
0>
b1011 -
b1011 1
b110 "
b11111111111111111111111111110110 *
b100 %
b100 ,
b100 (
#100
0<
0:
b10 3
06
b101 !
b101 .
b101 2
17
05
b1010 -
b1010 1
b101 "
b11111111111111111111111111110101 *
b101 %
b101 ,
b101 (
#102
1A
1:
1?
16
07
b11 3
1;
b100 !
b100 .
b100 2
0<
15
09
b1001 -
b1001 1
b100 "
b11111111111111111111111111110100 *
b110 %
b110 ,
b110 (
#104
0A
0?
0;
1<
0:
b0 3
06
b11 !
b11 .
b11 2
17
05
b1000 -
b1000 1
b11 "
b11111111111111111111111111110011 *
b111 %
b111 ,
b111 (
#106
1D
1@
1?
0A
1/
0E
1;
15
19
1>
0C
1:
b111 -
b111 1
b111 3
16
b11 !
b11 .
b11 2
17
14
b11 *
b1000 %
b1000 ,
b1011 $
b1011 +
b1011 0
b11111111111111111111111111111011 '
b11111111111111111111111111111000 (
#107
0&
#108
b10 !
b10 .
b10 2
07
05
b110 -
b110 1
b10 "
b10 *
b1001 %
b1001 ,
b11111111111111111111111111111001 (
#110
17
b1 !
b1 .
b1 2
0<
15
09
b101 -
b101 1
b1 "
b1 *
b1010 %
b1010 ,
b11111111111111111111111111111010 (
#112
b0 !
b0 .
b0 2
07
05
b100 -
b100 1
b0 "
b0 *
b1011 %
b1011 ,
b11111111111111111111111111111011 (
#114
0/
1E
0D
17
1<
b11 3
0@
b1111 !
b1111 .
b1111 2
1A
15
19
0>
b11 -
b11 1
b1111 "
b11111111111111111111111111111111 *
b1100 %
b1100 ,
b11111111111111111111111111111100 (
#116
b1110 !
b1110 .
b1110 2
07
05
b10 -
b10 1
b1110 "
b11111111111111111111111111111110 *
b1101 %
b1101 ,
b11111111111111111111111111111101 (
#118
17
b1101 !
b1101 .
b1101 2
0<
15
09
b1 -
b1 1
b1101 "
b11111111111111111111111111111101 *
b1110 %
b1110 ,
b11111111111111111111111111111110 (
#120
b1100 !
b1100 .
b1100 2
07
05
b0 -
b0 1
b1100 "
b11111111111111111111111111111100 *
b1111 %
b1111 ,
b11111111111111111111111111111111 (
#122
1D
17
1<
b111 3
1@
0A
1/
b1011 !
b1011 .
b1011 2
1E
15
19
1>
1C
b1111 -
b1111 1
b1011 "
b11111111111111111111111111111011 *
b0 %
b0 ,
b0 (
#124
b1010 !
b1010 .
b1010 2
07
05
b1110 -
b1110 1
b1010 "
b11111111111111111111111111111010 *
b1 %
b1 ,
b1 (
#126
17
b1001 !
b1001 .
b1001 2
0<
15
09
b1101 -
b1101 1
b1001 "
b11111111111111111111111111111001 *
b10 %
b10 ,
b10 (
#128
b1000 !
b1000 .
b1000 2
07
05
b1100 -
b1100 1
b1000 "
b11111111111111111111111111111000 *
b11 %
b11 ,
b11 (
#130
0E
0D
17
1<
b11 3
0@
b111 !
b111 .
b111 2
1A
15
19
0>
b1011 -
b1011 1
b111 "
b11111111111111111111111111110111 *
b100 %
b100 ,
b100 (
#131
1&
#132
b110 !
b110 .
b110 2
07
05
b1010 -
b1010 1
b110 "
b11111111111111111111111111110110 *
b101 %
b101 ,
b101 (
#134
17
b101 !
b101 .
b101 2
0<
15
09
b1001 -
b1001 1
b101 "
b11111111111111111111111111110101 *
b110 %
b110 ,
b110 (
#136
b100 !
b100 .
b100 2
07
05
b1000 -
b1000 1
b100 "
b11111111111111111111111111110100 *
b111 %
b111 ,
b111 (
#138
15
19
1>
0C
1:
1?
1D
b111 -
b111 1
16
07
1;
0<
b111 3
1@
b100 !
b100 .
b100 2
1A
04
08
1=
b100 *
b1000 %
b1000 ,
b1100 $
b1100 +
b1100 0
b11111111111111111111111111111100 '
b11111111111111111111111111111000 (
#139
0&
#140
0A
0?
0;
1<
0:
b100 3
06
b11 !
b11 .
b11 2
17
05
b110 -
b110 1
b11 "
b11 *
b1001 %
b1001 ,
b11111111111111111111111111111001 (
#142
1:
b101 3
16
07
b10 !
b10 .
b10 2
1<
15
09
b101 -
b101 1
b10 "
b10 *
b1010 %
b1010 ,
b11111111111111111111111111111010 (
#144
0<
0:
b100 3
06
b1 !
b1 .
b1 2
17
05
b100 -
b100 1
b1 "
b1 *
b1011 %
b1011 ,
b11111111111111111111111111111011 (
#146
1?
1;
1/
0E
1:
1D
16
07
0<
b111 3
1@
b0 !
b0 .
b0 2
0A
15
19
0>
b11 -
b11 1
b0 "
b0 *
b1100 %
b1100 ,
b11111111111111111111111111111100 (
#148
0/
1E
0D
0@
1A
0?
0;
1<
0:
b0 3
06
b1111 !
b1111 .
b1111 2
17
05
b10 -
b10 1
b1111 "
b11111111111111111111111111111111 *
b1101 %
b1101 ,
b11111111111111111111111111111101 (
#150
1:
b1 3
16
07
b1110 !
b1110 .
b1110 2
1<
15
09
b1 -
b1 1
b1110 "
b11111111111111111111111111111110 *
b1110 %
b1110 ,
b11111111111111111111111111111110 (
#152
0<
0:
b0 3
06
b1101 !
b1101 .
b1101 2
17
05
b0 -
b0 1
b1101 "
b11111111111111111111111111111101 *
b1111 %
b1111 ,
b11111111111111111111111111111111 (
#154
1?
1;
1:
1D
16
07
0<
b111 3
1@
1A
1/
b1100 !
b1100 .
b1100 2
1E
15
19
1>
1C
b1111 -
b1111 1
b1100 "
b11111111111111111111111111111100 *
b0 %
b0 ,
b0 (
#156
0A
0?
0;
1<
0:
b100 3
06
b1011 !
b1011 .
b1011 2
17
05
b1110 -
b1110 1
b1011 "
b11111111111111111111111111111011 *
b1 %
b1 ,
b1 (
#158
1:
b101 3
16
07
b1010 !
b1010 .
b1010 2
1<
15
09
b1101 -
b1101 1
b1010 "
b11111111111111111111111111111010 *
b10 %
b10 ,
b10 (
#160
0<
0:
b100 3
06
b1001 !
b1001 .
b1001 2
17
05
b1100 -
b1100 1
b1001 "
b11111111111111111111111111111001 *
b11 %
b11 ,
b11 (
#162
1?
1;
1E
1:
1D
16
07
0<
b111 3
1@
b1000 !
b1000 .
b1000 2
0A
15
19
0>
b1011 -
b1011 1
b1000 "
b11111111111111111111111111111000 *
b100 %
b100 ,
b100 (
#164
0E
0D
0@
1A
0?
0;
1<
0:
b0 3
06
b111 !
b111 .
b111 2
17
05
b1010 -
b1010 1
b111 "
b11111111111111111111111111110111 *
b101 %
b101 ,
b101 (
#165
1&
#166
1:
b1 3
16
07
b110 !
b110 .
b110 2
1<
15
09
b1001 -
b1001 1
b110 "
b11111111111111111111111111110110 *
b110 %
b110 ,
b110 (
#168
0<
0:
b0 3
06
b101 !
b101 .
b101 2
17
05
b1000 -
b1000 1
b101 "
b11111111111111111111111111110101 *
b111 %
b111 ,
b111 (
#170
1D
1?
1@
1A
1/
0E
1;
15
19
1>
0C
1:
b111 -
b111 1
b111 3
16
b101 !
b101 .
b101 2
17
14
b101 *
b1000 %
b1000 ,
b1101 $
b1101 +
b1101 0
b11111111111111111111111111111101 '
b11111111111111111111111111111000 (
#171
0&
#172
b100 !
b100 .
b100 2
07
05
b110 -
b110 1
b100 "
b100 *
b1001 %
b1001 ,
b11111111111111111111111111111001 (
#174
0A
0?
17
b101 3
0;
b11 !
b11 .
b11 2
1<
15
09
b101 -
b101 1
b11 "
b11 *
b1010 %
b1010 ,
b11111111111111111111111111111010 (
#176
b10 !
b10 .
b10 2
07
05
b100 -
b100 1
b10 "
b10 *
b1011 %
b1011 ,
b11111111111111111111111111111011 (
#178
1/
0E
1?
1D
17
1;
0<
b111 3
1@
b1 !
b1 .
b1 2
0A
15
19
0>
b11 -
b11 1
b1 "
b1 *
b1100 %
b1100 ,
b11111111111111111111111111111100 (
#180
b0 !
b0 .
b0 2
07
05
b10 -
b10 1
b0 "
b0 *
b1101 %
b1101 ,
b11111111111111111111111111111101 (
#182
0/
1E
0D
0@
1A
0?
17
b1 3
0;
b1111 !
b1111 .
b1111 2
1<
15
09
b1 -
b1 1
b1111 "
b11111111111111111111111111111111 *
b1110 %
b1110 ,
b11111111111111111111111111111110 (
#184
b1110 !
b1110 .
b1110 2
07
05
b0 -
b0 1
b1110 "
b11111111111111111111111111111110 *
b1111 %
b1111 ,
b11111111111111111111111111111111 (
#186
1?
1D
17
1;
0<
b111 3
1@
1A
1/
b1101 !
b1101 .
b1101 2
1E
15
19
1>
1C
b1111 -
b1111 1
b1101 "
b11111111111111111111111111111101 *
b0 %
b0 ,
b0 (
#188
b1100 !
b1100 .
b1100 2
07
05
b1110 -
b1110 1
b1100 "
b11111111111111111111111111111100 *
b1 %
b1 ,
b1 (
#190
0A
0?
17
b101 3
0;
b1011 !
b1011 .
b1011 2
1<
15
09
b1101 -
b1101 1
b1011 "
b11111111111111111111111111111011 *
b10 %
b10 ,
b10 (
#192
b1010 !
b1010 .
b1010 2
07
05
b1100 -
b1100 1
b1010 "
b11111111111111111111111111111010 *
b11 %
b11 ,
b11 (
#194
1E
1?
1D
17
1;
0<
b111 3
1@
b1001 !
b1001 .
b1001 2
0A
15
19
0>
b1011 -
b1011 1
b1001 "
b11111111111111111111111111111001 *
b100 %
b100 ,
b100 (
#196
b1000 !
b1000 .
b1000 2
07
05
b1010 -
b1010 1
b1000 "
b11111111111111111111111111111000 *
b101 %
b101 ,
b101 (
#198
0E
0D
0@
1A
0?
17
b1 3
0;
b111 !
b111 .
b111 2
1<
15
09
b1001 -
b1001 1
b111 "
b11111111111111111111111111110111 *
b110 %
b110 ,
b110 (
#199
1&
#200
b110 !
b110 .
b110 2
07
05
b1000 -
b1000 1
b110 "
b11111111111111111111111111110110 *
b111 %
b111 ,
b111 (
#202
1D
1/
0E
1@
15
19
1>
0C
1:
1?
b111 -
b111 1
16
07
b111 3
1;
b110 !
b110 .
b110 2
1<
04
18
b110 *
b1000 %
b1000 ,
b1110 $
b1110 +
b1110 0
b11111111111111111111111111111110 '
b11111111111111111111111111111000 (
#203
0&
#204
0<
0:
b110 3
06
b101 !
b101 .
b101 2
17
05
b110 -
b110 1
b101 "
b101 *
b1001 %
b1001 ,
b11111111111111111111111111111001 (
#206
1A
1:
1?
16
07
b111 3
1;
b100 !
b100 .
b100 2
0<
15
09
b101 -
b101 1
b100 "
b100 *
b1010 %
b1010 ,
b11111111111111111111111111111010 (
#208
0A
0?
0;
1<
0:
b100 3
06
b11 !
b11 .
b11 2
17
05
b100 -
b100 1
b11 "
b11 *
b1011 %
b1011 ,
b11111111111111111111111111111011 (
#210
1/
0E
1:
1?
1D
16
07
1;
1<
b111 3
1@
b10 !
b10 .
b10 2
0A
15
19
0>
b11 -
b11 1
b10 "
b10 *
b1100 %
b1100 ,
b11111111111111111111111111111100 (
#212
0<
0:
b110 3
06
b1 !
b1 .
b1 2
17
05
b10 -
b10 1
b1 "
b1 *
b1101 %
b1101 ,
b11111111111111111111111111111101 (
#214
1/
0E
1D
1@
0A
1:
1?
16
07
b111 3
1;
b0 !
b0 .
b0 2
0<
15
09
b1 -
b1 1
b0 "
b0 *
b1110 %
b1110 ,
b11111111111111111111111111111110 (
#216
0/
1E
0D
0@
1A
0?
0;
1<
0:
b0 3
06
b1111 !
b1111 .
b1111 2
17
05
b0 -
b0 1
b1111 "
b11111111111111111111111111111111 *
b1111 %
b1111 ,
b11111111111111111111111111111111 (
#218
1:
1?
1D
16
07
1;
1<
b111 3
1@
1A
1/
b1110 !
b1110 .
b1110 2
1E
15
19
1>
1C
b1111 -
b1111 1
b1110 "
b11111111111111111111111111111110 *
b0 %
b0 ,
b0 (
#220
0<
0:
b110 3
06
b1101 !
b1101 .
b1101 2
17
05
b1110 -
b1110 1
b1101 "
b11111111111111111111111111111101 *
b1 %
b1 ,
b1 (
#222
1A
1:
1?
16
07
b111 3
1;
b1100 !
b1100 .
b1100 2
0<
15
09
b1101 -
b1101 1
b1100 "
b11111111111111111111111111111100 *
b10 %
b10 ,
b10 (
#224
0A
0?
0;
1<
0:
b100 3
06
b1011 !
b1011 .
b1011 2
17
05
b1100 -
b1100 1
b1011 "
b11111111111111111111111111111011 *
b11 %
b11 ,
b11 (
#226
1E
1:
1?
1D
16
07
1;
1<
b111 3
1@
b1010 !
b1010 .
b1010 2
0A
15
19
0>
b1011 -
b1011 1
b1010 "
b11111111111111111111111111111010 *
b100 %
b100 ,
b100 (
#228
0<
0:
b110 3
06
b1001 !
b1001 .
b1001 2
17
05
b1010 -
b1010 1
b1001 "
b11111111111111111111111111111001 *
b101 %
b101 ,
b101 (
#230
1E
1D
1@
0A
1:
1?
16
07
b111 3
1;
b1000 !
b1000 .
b1000 2
0<
15
09
b1001 -
b1001 1
b1000 "
b11111111111111111111111111111000 *
b110 %
b110 ,
b110 (
#232
0E
0D
0@
1A
0?
0;
1<
0:
b0 3
06
b111 !
b111 .
b111 2
17
05
b1000 -
b1000 1
b111 "
b11111111111111111111111111110111 *
b111 %
b111 ,
b111 (
#233
1&
#234
1D
1?
1@
1A
1/
0E
1;
15
19
1>
0C
1:
b111 -
b111 1
b111 3
16
b111 !
b111 .
b111 2
17
14
b111 *
b1000 %
b1000 ,
b1111 $
b1111 +
b1111 0
b11111111111111111111111111111111 '
b11111111111111111111111111111000 (
#235
0&
#236
b110 !
b110 .
b110 2
07
05
b110 -
b110 1
b110 "
b110 *
b1001 %
b1001 ,
b11111111111111111111111111111001 (
#238
17
b101 !
b101 .
b101 2
0<
15
09
b101 -
b101 1
b101 "
b101 *
b1010 %
b1010 ,
b11111111111111111111111111111010 (
#240
b100 !
b100 .
b100 2
07
05
b100 -
b100 1
b100 "
b100 *
b1011 %
b1011 ,
b11111111111111111111111111111011 (
#242
17
1<
b11 !
b11 .
b11 2
0A
15
19
0>
b11 -
b11 1
b11 "
b11 *
b1100 %
b1100 ,
b11111111111111111111111111111100 (
#244
b10 !
b10 .
b10 2
07
05
b10 -
b10 1
b10 "
b10 *
b1101 %
b1101 ,
b11111111111111111111111111111101 (
#246
17
b1 !
b1 .
b1 2
0<
15
09
b1 -
b1 1
b1 "
b1 *
b1110 %
b1110 ,
b11111111111111111111111111111110 (
#248
b0 !
b0 .
b0 2
07
05
b0 -
b0 1
b0 "
b0 *
b1111 %
b1111 ,
b11111111111111111111111111111111 (
#250
17
1<
1A
b1111 !
b1111 .
b1111 2
1E
15
19
1>
1C
b1111 -
b1111 1
b1111 "
b11111111111111111111111111111111 *
b0 %
b0 ,
b0 (
#252
b1110 !
b1110 .
b1110 2
07
05
b1110 -
b1110 1
b1110 "
b11111111111111111111111111111110 *
b1 %
b1 ,
b1 (
#254
17
b1101 !
b1101 .
b1101 2
0<
15
09
b1101 -
b1101 1
b1101 "
b11111111111111111111111111111101 *
b10 %
b10 ,
b10 (
#256
b1100 !
b1100 .
b1100 2
07
05
b1100 -
b1100 1
b1100 "
b11111111111111111111111111111100 *
b11 %
b11 ,
b11 (
#258
17
1<
b1011 !
b1011 .
b1011 2
0A
15
19
0>
b1011 -
b1011 1
b1011 "
b11111111111111111111111111111011 *
b100 %
b100 ,
b100 (
#260
b1010 !
b1010 .
b1010 2
07
05
b1010 -
b1010 1
b1010 "
b11111111111111111111111111111010 *
b101 %
b101 ,
b101 (
#262
17
b1001 !
b1001 .
b1001 2
0<
15
09
b1001 -
b1001 1
b1001 "
b11111111111111111111111111111001 *
b110 %
b110 ,
b110 (
#264
b1000 !
b1000 .
b1000 2
07
05
b1000 -
b1000 1
b1000 "
b11111111111111111111111111111000 *
b111 %
b111 ,
b111 (
#266
0/
15
19
1>
0C
1:
1?
1D
b111 -
b111 1
16
07
1;
0<
b111 3
1@
0A
b1000 !
b1000 .
b1000 2
1E
04
08
0=
0B
b1000 *
b1000 %
b1000 ,
b0 $
b0 +
b0 0
b0 '
b11111111111111111111111111111000 (
#267
1&
#268
0E
0D
0@
1A
0?
0;
1<
0:
b0 3
06
b111 !
b111 .
b111 2
17
05
b110 -
b110 1
b111 "
b111 *
b1001 %
b1001 ,
b11111111111111111111111111111001 (
#269
0&
#270
1:
b1 3
16
07
b110 !
b110 .
b110 2
1<
15
09
b101 -
b101 1
b110 "
b110 *
b1010 %
b1010 ,
b11111111111111111111111111111010 (
#272
0<
0:
b0 3
06
b101 !
b101 .
b101 2
17
05
b100 -
b100 1
b101 "
b101 *
b1011 %
b1011 ,
b11111111111111111111111111111011 (
