ex7/sat_count.v
module sat_count(clk, reset, branch, taken, prediction);
   parameter N=2;
   input clk, reset, branch, taken;
   output prediction;

   reg [1:0] state;

   always @(posedge clk) begin
     if (reset) state <= 'b0;			// reset state to 00
     else if (~branch) state <= state;		// preserve state
     else begin
       case (state)
         'b00: state <= taken ? 'b01 : 'b00;
         'b01: state <= taken ? 'b10 : 'b00;
         'b10: state <= taken ? 'b11 : 'b01;
         'b11: state <= taken ? 'b11 : 'b10;
         default: state <= 'bxx;        // should never get here code 
       endcase
     end
   end
   
   assign prediction = state[1];

endmodule

ex7/sat_count_tb.v
module main;
	reg clk, reset, taken, branch;
	wire prediction;
	
	integer error_num, expected, a, b;
	
	sat_count sat_count(.clk(clk), .reset(reset), .branch(branch), .taken(taken), .prediction(prediction));
	
	initial begin
		$dumpfile("waves.vcd");
		$dumpvars;
		
		expected = 0;
		
		clk = 1;
		reset = 1;
		taken = 0;
		branch = 0;
		#5;			// 5	
		reset = 0;
		branch = 1;
		taken = 1;
		#5;			// 10
		#10;		// 20
		expected = 1;
		#30;		// 50
		reset = 1;
		expected = 0;
		#5;			// 55
		reset = 0;
		taken = 0;
		#5;			// 60
		#10;		// 70	
		expected = 0;
		#10;		// 80
		taken = 1;
		#10;		//90
		expected = 1;
		#30;		// 120
		taken = 0;
		#10;		// 130
		expected = 0;
		#10;		// 140
		taken = 1;
		expected = 1;
		#30;		// 170
		taken = 0;
		#10;		// 180
		expected = 0;
		#30;		// 210
		
		
		$finish;
	end
	
	always #5 clk = ~clk;

endmodule

ex7/waves.vcd
$date
	Fri Dec 23 17:51:06 2022
$end
$version
	Icarus Verilog
$end
$timescale
	1s
$end
$scope module main $end
$var wire 1 ! prediction $end
$var reg 1 " branch $end
$var reg 1 # clk $end
$var reg 1 $ reset $end
$var reg 1 % taken $end
$var integer 32 & expected [31:0] $end
$scope module sat_count $end
$var wire 1 " branch $end
$var wire 1 # clk $end
$var wire 1 $ reset $end
$var wire 1 % taken $end
$var wire 1 ! prediction $end
$var reg 2 ' state [1:0] $end
$upscope $end
$upscope $end
$enddefinitions $end
#0
$dumpvars
b0 '
b0 &
0%
1$
1#
0"
0!
$end
#5
0#
1%
1"
0$
#10
b1 '
1#
#15
0#
#20
1!
b10 '
1#
b1 &
#25
0#
#30
b11 '
1#
#35
0#
#40
1#
#45
0#
#50
0!
b0 '
1#
b0 &
1$
#55
0#
0%
0$
#60
1#
#65
0#
#70
1#
#75
0#
#80
b1 '
1#
1%
#85
0#
#90
1!
b10 '
1#
b1 &
#95
0#
#100
b11 '
1#
#105
0#
#110
1#
#115
0#
#120
b10 '
1#
0%
#125
0#
#130
0!
b1 '
1#
b0 &
#135
0#
#140
1!
b10 '
1#
b1 &
1%
#145
0#
#150
b11 '
1#
#155
0#
#160
1#
#165
0#
#170
b10 '
1#
0%
#175
0#
#180
0!
b1 '
1#
b0 &
#185
0#
#190
b0 '
1#
